s1_orbits/__init__.py
s1_orbits/exceptions.py
s1_orbits/s1_orbits.py
s1_orbits-0.2.0.dist-info/licenses/LICENSE
s1_orbits-0.2.0.dist-info/METADATA
s1_orbits-0.2.0.dist-info/WHEEL
s1_orbits-0.2.0.dist-info/top_level.txt
s1_orbits-0.2.0.dist-info/RECORD
