Metadata-Version: 2.4
Name: s1_orbits
Version: 0.2.0
Summary: A Python utility for downloading Sentinel-1 Orbit files from the Registry of Open Data on AWS
Author-email: ASF APD/Tools Team <uaf-asf-apd@alaska.edu>
License-Expression: BSD-3-Clause
Project-URL: Homepage, https://github.com/ASFHyP3/sentinel1-orbits-py
Project-URL: Bug Tracker, https://github.com/ASFHyP3/sentinel1-orbits-py/issues
Classifier: Intended Audience :: Science/Research
Classifier: Natural Language :: English
Classifier: Operating System :: OS Independent
Classifier: Programming Language :: Python :: 3
Classifier: Programming Language :: Python :: 3.10
Classifier: Programming Language :: Python :: 3.11
Classifier: Programming Language :: Python :: 3.12
Classifier: Programming Language :: Python :: 3.13
Requires-Python: >=3.10
License-File: LICENSE
Requires-Dist: requests
Provides-Extra: develop
Requires-Dist: build; extra == "develop"
Requires-Dist: pytest; extra == "develop"
Requires-Dist: pytest-cov; extra == "develop"
Requires-Dist: responses; extra == "develop"
Requires-Dist: ruff; extra == "develop"
Requires-Dist: mypy; extra == "develop"
Dynamic: license-file
